CB2325NumericaG5/__init__.py
CB2325NumericaG5/aproximacao.py
CB2325NumericaG5/erros.py
CB2325NumericaG5/graficos_aproximacao.py
CB2325NumericaG5/integracao.py
CB2325NumericaG5/interpolacao.py
CB2325NumericaG5/raizes.py
cb2325numericag5-0.0.5.dist-info/licenses/LICENSE
cb2325numericag5-0.0.5.dist-info/METADATA
cb2325numericag5-0.0.5.dist-info/WHEEL
cb2325numericag5-0.0.5.dist-info/top_level.txt
cb2325numericag5-0.0.5.dist-info/RECORD
