Metadata-Version: 2.4
Name: CB2325NumericaG5
Version: 0.0.5
Summary: Biblioteca de cálculo numérico, contendo funcionalidades clássicas de análise numérica e recursos gráficos para visualização de resultados.
Author: Amon Vanderlei, André Oliveira, Carlos Santos, Davi Campos, Felipe Frohlich, Gabriel Dias, Lisandra Fagundes, Lucas Corazza, Lucas Oliveira, Nicole Freire
Author-email: Amon Vanderlei <al.amon.vanderlei@impatech.edu.br>, André Oliveira <al.andre.oliveira@impatech.edu.br>, Carlos Santos <al.carlos.santos@impatech.edu.br>, Davi Campos <al.davi.campos@impatech.edu.br>, Felipe Frohlich <al.felipe.frohlich@impatech.edu.br>, Gabriel Dias <al.gabriel.dias@impatech.edu.br>, Lisandra Fagundes <al.lisandra.fagundes@impatech.edu.br>, Lucas Corazza <al.lucas.corazza@impatech.edu.br>, Lucas Oliveira <al.lucas.oliveira@impatech.edu.br>, Nicole Freire <al.nicole
License-Expression: MIT
Keywords: Cálculo numérico,Análise numérica
Classifier: Programming Language :: Python :: 3
Requires-Python: >=3.8
License-File: LICENSE
Requires-Dist: sympy
Requires-Dist: matplotlib
Requires-Dist: numpy
Dynamic: author
Dynamic: license-file
Dynamic: requires-python
